vetl/__init__.py
vetl/engine.py
vetl/tool.py
vetl/core/__init__.py
vetl/core/db.py
vetl/core/tunnel.py
pypetl-0.0.2.dist-info/METADATA
pypetl-0.0.2.dist-info/WHEEL
pypetl-0.0.2.dist-info/top_level.txt
pypetl-0.0.2.dist-info/RECORD
