Metadata-Version: 2.1
Name: pypetl
Version: 0.0.2
Summary: Python ETL Tools
Home-page: https://github.com/asyraf-adianto/pypetl
Author: Asyraf N. Adianto
Author-email: asyraf.adianto@renos.id
License: MIT
Platform: UNKNOWN
Requires-Python: >=3.0
Requires-Dist: pandas (>=1.0.3)
Requires-Dist: petl (>=1.7.0)
Requires-Dist: redshift-connector (>=2.0.908)
Requires-Dist: psycopg2-binary (>=2.9.3)
Requires-Dist: paramiko (>=2.11.0)
Requires-Dist: sshtunnel (>=0.4.0)
